unimeth/__init__.py
unimeth/config.py
unimeth/inference.py
unimeth/run_unimeth_acc.py
unimeth/unimeth.py
unimeth/util.py
unimeth/extract/__init__.py
unimeth/extract/bam.py
unimeth/extract/feature.py
unimeth/extract/patcher.py
unimeth/extract/processors.py
unimeth/extract/reader.py
unimeth/extract/util.py
unimeth/model/__init__.py
unimeth/model/data.py
unimeth/model/model.py
unimeth/model/module.py
unimeth/model/util.py
unimeth-0.0.2.dist-info/METADATA
unimeth-0.0.2.dist-info/WHEEL
unimeth-0.0.2.dist-info/entry_points.txt
unimeth-0.0.2.dist-info/licenses/LICENSE
unimeth-0.0.2.dist-info/RECORD
