Metadata-Version: 2.4
Name: unimeth
Version: 0.0.2
Summary: unimeth
Project-URL: Homepage, https://github.com/sekeyWang/Unimeth
Project-URL: Bug Tracker, https://github.com/sekeyWang/Unimeth/issues
Author-email: Shaokai Wang <shaokaiwang@ust.hk>
License: BSD-3-Clause-Clear license
License-File: LICENSE
Requires-Python: >=3.12
Requires-Dist: accelerate==1.8.1
Requires-Dist: numpy==1.26.4
Requires-Dist: pod5==0.3.15
Requires-Dist: pysam>=0.23.3
Requires-Dist: torch==2.4.0
Requires-Dist: tqdm==4.66.5
Requires-Dist: transformers==4.53.0
